Examples/__init__.py
Examples/basic_ssl_example.py
Examples/batching_example.py
Examples/cloud_dedicated_query.py
Examples/cloud_dedicated_write.py
Examples/config.py
Examples/flight_options_example.py
Examples/handle_http_error.py
Examples/handle_query_error.py
Examples/pandas_write.py
Examples/query_async.py
Examples/query_type.py
influxdb3_python-0.16.0.dist-info/licenses/LICENSE
influxdb_client_3/__init__.py
influxdb_client_3/py.typed
influxdb_client_3/read_file.py
influxdb_client_3/version.py
influxdb_client_3/exceptions/__init__.py
influxdb_client_3/exceptions/exceptions.py
influxdb_client_3/query/__init__.py
influxdb_client_3/query/query_api.py
influxdb_client_3/write_client/__init__.py
influxdb_client_3/write_client/configuration.py
influxdb_client_3/write_client/extras.py
influxdb_client_3/write_client/rest.py
influxdb_client_3/write_client/_sync/__init__.py
influxdb_client_3/write_client/_sync/api_client.py
influxdb_client_3/write_client/_sync/rest.py
influxdb_client_3/write_client/client/__init__.py
influxdb_client_3/write_client/client/_base.py
influxdb_client_3/write_client/client/influxdb_client.py
influxdb_client_3/write_client/client/logging_handler.py
influxdb_client_3/write_client/client/warnings.py
influxdb_client_3/write_client/client/write_api.py
influxdb_client_3/write_client/client/util/__init__.py
influxdb_client_3/write_client/client/util/date_utils.py
influxdb_client_3/write_client/client/util/date_utils_pandas.py
influxdb_client_3/write_client/client/util/helpers.py
influxdb_client_3/write_client/client/util/multiprocessing_helper.py
influxdb_client_3/write_client/client/write/__init__.py
influxdb_client_3/write_client/client/write/dataframe_serializer.py
influxdb_client_3/write_client/client/write/point.py
influxdb_client_3/write_client/client/write/polars_dataframe_serializer.py
influxdb_client_3/write_client/client/write/retry.py
influxdb_client_3/write_client/domain/__init__.py
influxdb_client_3/write_client/domain/write_precision.py
influxdb3_python-0.16.0.dist-info/METADATA
influxdb3_python-0.16.0.dist-info/WHEEL
influxdb3_python-0.16.0.dist-info/top_level.txt
influxdb3_python-0.16.0.dist-info/RECORD
