Metadata-Version: 2.4
Name: influxdb3-python
Version: 0.16.0
Summary: Community Python client for InfluxDB 3.0
Home-page: https://github.com/InfluxCommunity/influxdb3-python
Author: InfluxData
Author-email: contact@influxdata.com
Classifier: Development Status :: 4 - Beta
Classifier: Intended Audience :: Developers
Classifier: License :: OSI Approved :: MIT License
Classifier: Programming Language :: Python :: 3.8
Classifier: Programming Language :: Python :: 3.9
Classifier: Programming Language :: Python :: 3.10
Classifier: Programming Language :: Python :: 3.11
Classifier: Programming Language :: Python :: 3.12
Classifier: Programming Language :: Python :: 3.13
Requires-Python: >=3.8
License-File: LICENSE
Requires-Dist: reactivex>=4.0.4
Requires-Dist: certifi>=14.05.14
Requires-Dist: python_dateutil>=2.5.3
Requires-Dist: urllib3>=1.26.0
Requires-Dist: pyarrow>=8.0.0
Provides-Extra: pandas
Requires-Dist: pandas; extra == "pandas"
Provides-Extra: polars
Requires-Dist: polars; extra == "polars"
Provides-Extra: dataframe
Requires-Dist: pandas; extra == "dataframe"
Requires-Dist: polars; extra == "dataframe"
Provides-Extra: test
Requires-Dist: pytest; extra == "test"
Requires-Dist: pytest-cov; extra == "test"
Requires-Dist: pytest-httpserver; extra == "test"
Dynamic: author
Dynamic: author-email
Dynamic: classifier
Dynamic: description
Dynamic: description-content-type
Dynamic: home-page
Dynamic: license-file
Dynamic: provides-extra
Dynamic: requires-dist
Dynamic: requires-python
Dynamic: summary
